LICENSE
MANIFEST.in
README.md
requirements.txt
setup.cfg
setup.py
gnosis_epl/__init__.py
gnosis_epl/main.py
gnosis_epl.egg-info/PKG-INFO
gnosis_epl.egg-info/SOURCES.txt
gnosis_epl.egg-info/dependency_links.txt
gnosis_epl.egg-info/not-zip-safe
gnosis_epl.egg-info/requires.txt
gnosis_epl.egg-info/top_level.txt
gnosis_epl/grammar/GnosisEPLLexer.py
gnosis_epl/grammar/GnosisEPLListener.py
gnosis_epl/grammar/GnosisEPLParser.py
gnosis_epl/grammar/epl_listener.py
tests/__init__.py
tests/test_grammar.py