Metadata-Version: 2.1
Name: gnosis-epl
Version: 0.11.3
Summary: Gnosis EPL python package
Author: Felipe Arruda Pontes
Author-email: felipe.arruda.pontes@insight-centre.org
License: Apache License, Version 2.0
License-File: LICENSE
